README.rst
setup.py
electronics/__init__.py
electronics/device.py
electronics/gpio.py
electronics/pin.py
electronics/devices/__init__.py
electronics/devices/bmp180.py
electronics/devices/hmc5883l.py
electronics/devices/lm75.py
electronics/devices/mcp23017.py
electronics/devices/mpu6050.py
electronics/devices/sevensegment.py
electronics/gateways/__init__.py
electronics/gateways/buspirate.py
electronics/gateways/linuxdevice.py
electronics/gateways/mock.py
pyelectronics.egg-info/PKG-INFO
pyelectronics.egg-info/SOURCES.txt
pyelectronics.egg-info/dependency_links.txt
pyelectronics.egg-info/top_level.txt