Metadata-Version: 1.1
Name: pyelectronics
Version: 0.1.4
Summary: Python 3 library for working with electronics
Home-page: https://github.com/MartijnBraam/pyElectronics
Author: Martijn Braam
Author-email: martijn@brixit.nl
License: MIT
Keywords: electronics,spi,i2c,buspirate
Platform: UNKNOWN
Classifier: Programming Language :: Python
Classifier: Programming Language :: Python :: 3
Classifier: Development Status :: 4 - Beta
Classifier: Operating System :: POSIX :: Linux
Classifier: License :: OSI Approved :: MIT License
